agenthub_tools/duckduckgo/__init__.py
agenthub_tools/duckduckgo/tools.py
agenthub_tools_duckduckgo-0.0.6.dist-info/METADATA
agenthub_tools_duckduckgo-0.0.6.dist-info/WHEEL
agenthub_tools_duckduckgo-0.0.6.dist-info/top_level.txt
agenthub_tools_duckduckgo-0.0.6.dist-info/RECORD
